flake8_import_order_pep_8_app.py
flake8_import_order_pep8app-0.2.1.dist-info/LICENSE
flake8_import_order_pep8app-0.2.1.dist-info/METADATA
flake8_import_order_pep8app-0.2.1.dist-info/WHEEL
flake8_import_order_pep8app-0.2.1.dist-info/entry_points.txt
flake8_import_order_pep8app-0.2.1.dist-info/top_level.txt
flake8_import_order_pep8app-0.2.1.dist-info/RECORD
